odoo/addons/base_cron_exclusion/README.rst
odoo/addons/base_cron_exclusion/__init__.py
odoo/addons/base_cron_exclusion/__manifest__.py
odoo/addons/base_cron_exclusion/i18n/base_cron_exclusion.pot
odoo/addons/base_cron_exclusion/i18n/cs_CZ.po
odoo/addons/base_cron_exclusion/i18n/es.po
odoo/addons/base_cron_exclusion/i18n/fr.po
odoo/addons/base_cron_exclusion/i18n/zh_CN.po
odoo/addons/base_cron_exclusion/models/__init__.py
odoo/addons/base_cron_exclusion/models/ir_cron.py
odoo/addons/base_cron_exclusion/readme/CONTRIBUTORS.rst
odoo/addons/base_cron_exclusion/readme/DESCRIPTION.rst
odoo/addons/base_cron_exclusion/readme/USAGE.rst
odoo/addons/base_cron_exclusion/static/description/icon.png
odoo/addons/base_cron_exclusion/static/description/index.html
odoo/addons/base_cron_exclusion/views/ir_cron_view.xml
odoo12_addon_base_cron_exclusion-12.0.1.0.0.99.dev10.dist-info/METADATA
odoo12_addon_base_cron_exclusion-12.0.1.0.0.99.dev10.dist-info/WHEEL
odoo12_addon_base_cron_exclusion-12.0.1.0.0.99.dev10.dist-info/top_level.txt
odoo12_addon_base_cron_exclusion-12.0.1.0.0.99.dev10.dist-info/RECORD
